csv_dataset/__init__.py
csv_dataset/common.py
csv_dataset/dataset.py
csv_dataset/normalizer.py
csv_dataset/reader.py
csv_dataset-3.5.0.dist-info/LICENSE
csv_dataset-3.5.0.dist-info/METADATA
csv_dataset-3.5.0.dist-info/WHEEL
csv_dataset-3.5.0.dist-info/top_level.txt
csv_dataset-3.5.0.dist-info/RECORD
