Metadata-Version: 2.1
Name: csv-dataset
Version: 3.5.0
Summary: csv-dataset helps to read csv files and create descriptive and efficient input pipelines for deep learning in a streaming fashion
Home-page: https://github.com/kaelzhang/python-csv-dataset
Author: kaelzhang
Author-email: 
License: MIT
Keywords: csv-dataset
Platform: UNKNOWN
Classifier: Topic :: Software Development :: Libraries :: Python Modules
Classifier: Programming Language :: Python :: 3.7
Classifier: Programming Language :: Python :: 3.8
Classifier: Programming Language :: Python :: Implementation :: PyPy
Classifier: Topic :: Software Development :: Libraries :: Python Modules
Classifier: License :: OSI Approved :: MIT License
Requires-Python: >=3.7
